{
  "2025-12-24": {
    "tokens": [
      {
        "token": "DOOD",
        "score": 176
      },
      {
        "token": "MERL",
        "score": 174
      },
      {
        "token": "SKY",
        "score": 172
      },
      {
        "token": "MNT",
        "score": 168
      },
      {
        "token": "VVV",
        "score": 168
      },
      {
        "token": "ZEC",
        "score": 168
      }
    ],
    "timestamp": "2025-12-24T23:50:19.015719"
  },
  "2025-12-25": {
    "tokens": [
      {
        "token": "DOOD",
        "score": 200
      },
      {
        "token": "MERL",
        "score": 198
      },
      {
        "token": "SKY",
        "score": 196
      },
      {
        "token": "VVV",
        "score": 193
      },
      {
        "token": "CC",
        "score": 192
      },
      {
        "token": "SYRUP",
        "score": 190
      }
    ],
    "timestamp": "2025-12-25T23:49:06.994786"
  },
  "2025-12-26": {
    "tokens": [
      {
        "token": "DOOD",
        "score": 198
      },
      {
        "token": "CC",
        "score": 196
      },
      {
        "token": "MERL",
        "score": 193
      },
      {
        "token": "VVV",
        "score": 193
      },
      {
        "token": "SYRUP",
        "score": 189
      },
      {
        "token": "SKY",
        "score": 189
      }
    ],
    "timestamp": "2025-12-26T23:49:27.926189"
  },
  "2025-12-27": {
    "tokens": [
      {
        "token": "CC",
        "score": 172
      },
      {
        "token": "SKY",
        "score": 170
      },
      {
        "token": "MERL",
        "score": 168
      },
      {
        "token": "ZEC",
        "score": 166
      },
      {
        "token": "ACE",
        "score": 164
      },
      {
        "token": "PAXG",
        "score": 161
      }
    ],
    "timestamp": "2025-12-27T20:18:34.470428"
  },
  "2025-12-28": {
    "tokens": [
      {
        "token": "CC",
        "score": 182
      },
      {
        "token": "SKY",
        "score": 180
      },
      {
        "token": "ZEC",
        "score": 178
      },
      {
        "token": "ACE",
        "score": 176
      },
      {
        "token": "TST",
        "score": 173
      },
      {
        "token": "MERL",
        "score": 172
      }
    ],
    "timestamp": "2025-12-28T01:25:28.890811"
  }
}